erdantic/__init__.py
erdantic/__main__.py
erdantic/_logging.py
erdantic/_repr_utils.py
erdantic/_version.py
erdantic/cli.py
erdantic/convenience.py
erdantic/core.py
erdantic/d2.py
erdantic/exceptions.py
erdantic/py.typed
erdantic/typing_utils.py
erdantic/examples/__init__.py
erdantic/examples/attrs.py
erdantic/examples/dataclasses.py
erdantic/examples/msgspec.py
erdantic/examples/pydantic.py
erdantic/examples/pydantic_v1.py
erdantic/plugins/__init__.py
erdantic/plugins/attrs.py
erdantic/plugins/dataclasses.py
erdantic/plugins/msgspec.py
erdantic/plugins/pydantic.py
erdantic-1.2.0.dist-info/METADATA
erdantic-1.2.0.dist-info/WHEEL
erdantic-1.2.0.dist-info/entry_points.txt
erdantic-1.2.0.dist-info/licenses/LICENSE
erdantic-1.2.0.dist-info/RECORD
