Metadata-Version: 2.4
Name: erdantic
Version: 1.2.0
Summary: Entity relationship diagrams for Python data model classes like Pydantic.
Project-URL: Repository, https://github.com/drivendataorg/erdantic
Project-URL: Documentation, https://erdantic.drivendata.org/
Project-URL: Bug Tracker, https://github.com/drivendataorg/erdantic/issues
Project-URL: Changelog, https://erdantic.drivendata.org/stable/changelog/
Author: Jay Qi
Author-email: DrivenData <info@drivendata.org>
License: MIT License
License-File: LICENSE
Keywords: attrs,dataclasses,entity relationship diagram,erd,msgspec,pydantic
Classifier: Framework :: Pydantic
Classifier: Framework :: Pydantic :: 2
Classifier: Intended Audience :: Developers
Classifier: License :: OSI Approved :: MIT License
Classifier: Operating System :: OS Independent
Classifier: Programming Language :: Python :: 3
Classifier: Programming Language :: Python :: 3.9
Classifier: Programming Language :: Python :: 3.10
Classifier: Programming Language :: Python :: 3.11
Classifier: Programming Language :: Python :: 3.12
Classifier: Programming Language :: Python :: 3.13
Classifier: Topic :: Software Development :: Code Generators
Requires-Python: >=3.9
Requires-Dist: pydantic-core
Requires-Dist: pydantic>=2
Requires-Dist: pygraphviz
Requires-Dist: sortedcontainers-pydantic
Requires-Dist: typenames>=1.3
Requires-Dist: typer
Requires-Dist: typing-extensions>4; python_version < '3.12'
Provides-Extra: attrs
Requires-Dist: attrs; extra == 'attrs'
Provides-Extra: msgspec
Requires-Dist: msgspec; extra == 'msgspec'
